[
  {
    "id": 1,
    "type": "общий",
    "setup": "Что сказала рыба, когда ударилась о стену?",
    "Punchline": "Плотина."
  },
  {
    "id": 2,
    "type": "общий",
    "setup": "Как заставить танцевать ткани?",
    "punchline": "Вы добавили немного буги-вуги."
  },
  {
    "id": 3,
    "type": "общий",
    "setup": "Какой пароль у Фореста Гампа?",
    "punchline": "1Forrest1"
  },
  {
    "id": 4,
    "type": "общий",
    "setup": "Как назвать ремень, сделанный из часов?",
    "punchline": "Тали времени."
  },
  {
    "id": 5,
    "type": "общий",
    "setup": "Почему велосипеды не могут стоять самостоятельно?",
    "punchline": "Они двое устали"
  },
  {
    "id": 6,
    "type": "общий",
    "setup": "Как поезд ест?",
    "punchline": "Он идет жевать, жевать"
  },
  {
    "id": 7,
    "type": "общий",
    "setup": "Что вы называете поющим ноутбуком",
    "punchline": "Делл"
  },
  {
    "id": 8,
    "type": "общий",
    "setup": "Сколько губ у цветка?",
    "punchline": "Тюльпаны"
  },
  {
    "id": 9,
    "type": "общий",
    "setup": "Как организовать космическую вечеринку?",
    "punchline": "Ты, планета"
  },
  {
    "id": 10,
    "type": "общий",
    "setup": "Какую обувь носит вор?",
    "Punchline": "Кроссовки"
  },
  {
    "id": 11,
    "type": "общий",
    "setup": "В какое время лучше идти к стоматологу?",
    "punchline": "Зуб болит."
  },
  {
    "id": 12,
    "type": "тук-тук",
    "setup": "Тук-тук. \n Кто там? \n Сломанный карандаш. \n Сломанный карандаш кто?",
    "punchline": "Неважно. Это бессмысленно."
  },
  {
    "id": 13,
    "type": "тук-тук",
    "setup": "Тук-тук. \n Кто там? \n Коровы идут. \n Коровы идут кто?",
    "punchline": "Нет, коровы мычат."
  },
  {
    "id": 14,
    "type": "тук-тук",
    "setup": "Тук-тук. \n Кто там? \n Старушка. \n Старушка кто?",
    "punchline": "Я не знал, что ты умеешь петь йодлем!"
  },
  {
    "id": 15,
    "type": "программирование",
    "setup": "Что хорошего в логическом значении?",
    "punchline": "Даже если вы ошибаетесь, вы ошибаетесь лишь немного."
  },
  {
    "id": 16,
    "type": "программирование",
    "setup": "Какой объектно-ориентированный способ стать богатым?",
    "Punchline": "Наследие"
  },
  {
    "id": 17,
    "type": "программирование",
    "setup": "Где любят тусоваться программисты?",
    "punchline": "Бар Фу."
  },
  {
    "id": 18,
    "type": "программирование",
    "setup": "Почему программист уволился с работы?",
    "punchline": "Потому что он не получил массивы."
  },
  {
    "id": 19,
    "type": "общий",
    "setup": "Вы слышали о двух гонках тутового шелкопряда?",
    "punchline": "Все закончилось ничьей."
  },
  {
    "id": 19,
    "type": "общий",
    "setup": "AABCEHACBACDEE?",
    "punchline": "AABCEHACBACDEE?"
  },
  {
    "id": 20,
    "type": "общий",
    "setup": "Как назвать смеющийся мотоцикл?",
    "Punchline": "Ямахахахаха."
  },
  {
    "id": 21,
    "type": "общий",
    "setup": "Термит заходит в бар и говорит...",
    "punchline": "'Где находится бар?'"
  },
  {
    "id": 22,
    "type": "общий",
    "setup": "Что К. С. Льюис хранит в задней части своего гардероба?",
    "punchline": "Дело в Нарнии!"
  },
  {
    "id": 23,
    "type": "программирование",
    "setup": "Почему программисты всегда путают Хэллоуин и Рождество?",
    "punchline": "Потому что 31 октября == 25 декабря"
  },
  {
    "id": 24,
    "type": "программирование",
    "setup": "SQL-запрос входит в бар, подходит к двум столам и спрашивает...",
    "punchline": "'Можно к вам присоединиться?'"
  },
  {
    "id": 25,
    "type": "программирование",
    "setup": "Сколько программистов нужно, чтобы поменять лампочку?",
    "punchline": "Нет, это аппаратная проблема"
  },
  {
    "id": 26,
    "type": "программирование",
    "setup": "Если посадить миллион обезьян за миллион клавиатур, одна из них в итоге напишет программу на Java",
    "punchline": "остальные будут писать на Perl"
  },
  {
    "id": 27,
    "type": "программирование",
    "setup": "['бедро', 'бедро']",
    "punchline": "(бедро бедра)"
  },
  {
    "id": 28,
    "type": "программирование",
    "setup": "Чтобы понять, что такое рекурсия...",
    "punchline": "Сначала вы должны понять, что такое рекурсия"
  },
  {
    "id": 29,
    "type": "программирование",
    "setup": "В этом мире есть 10 typeов людей...",
    "punchline": "Те, кто понимает двоичный код, и те, кто не понимает"
  },
  {
    "id": 30,
    "type": "общий",
    "setup": "Что сказал утка, когда покупал помаду?",
    "punchline": "Поместите это в мой счет"
  },
  {
    "id": 31,
    "type": "общий",
    "setup": "Что происходит с машиной лягушки, когда она ломается?",
    "punchline": "Это убирает жабу"
  },
  {
    "id": 32,
    "type": "общий",
    "setup": "Знаете ли вы, что первый картофель фри не готовили во Франции?",
    "Punchline": "их готовили в Греции"
  },
  {
    "id": 34,
    "type": "тук-тук",
    "setup": "Тук-тук. \n Кто здесь? \n Возможность.",
    "punchline": "Это невозможно. Возможность не приходит дважды!"
  },
  {
    "id": 35,
    "type": "программирование",
    "setup": "Почему Java-программисты носят очки?",
    "punchline": "Потому что они не C#"
  },
  {
    "id": 36,
    "type": "общий",
    "setup": "Почему гриб пригласили на вечеринку?",
    "punchline": "Потому что он был грибком."
  },
  {
    "id": 37,
    "type": "общий",
    "setup": "Почему гриб пригласили на вечеринку?",
    "punchline": "Потому что он был грибком."
  },
  {
    "id": 38,
    "type": "общий",
    "setup": "Я читаю книгу об антигравитации...",
    "punchline": "От этого невозможно оторваться"
  },
  {
    "id": 39,
    "type": "общий",
    "setup": "Если вы американец, когда заходите в ванную, и американец, когда выходите, то кто вы, когда находитесь там?",
    "punchline": "Европейский"
  },
  {
    "id": 40,
    "type": "общий",
    "setup": "Хочешь анекдот про бумажку?",
    "punchline": "Пошел нахуй"
  },
  {
    "id": 41,
    "type": "общий",
    "setup": "Я только что посмотрел документальный фильм о бобрах.",
    "punchline": "Это было лучшее шоу плотин, которое я когда-либо видел"
  },
  {
    "id": 42,
    "type": "общий",
    "setup": "Если вы видите ограбление в Apple Store...",
    "punchline": "Это делает вас iWitness?"
  },
  {
    "id": 43,
    "type": "общий",
    "setup": "Сэндвич с ветчиной заходит в бар и заказывает пиво. Бармен говорит...",
    "punchline": "Извините, здесь не подают еду"
  },
  {
    "id": 44,
    "type": "общий",
    "setup": "Почему Клайдсдейл дал пони стакан воды?",
    "punchline": "Потому что он был маленькой лошадкой"
  },
  {
    "id": 45,
    "type": "общий",
    "setup": "Если сварить клоуна...",
    "punchline": "У вас есть посмешище?"
  },
  {
    "id": 46,
    "type": "общий",
    "setup": "Наконец-то понял, почему мой завод целый день ничего не делает...",
    "punchline": "Он любит свой горшок."
  },
  {
    "id": 47,
    "type": "общий",
    "setup": "Не смотрите на затмение через дуршлаг.",
    "punchline": "Вы будете напрягать глаза."
  },
  {
    "id": 48,
    "type": "общий",
    "setup": "Я купил обувь у торговца наркотиками.",
    "punchline": "Я не знаю, чем он их зашнуровал, но я весь день спотыкался!"
  },
  {
    "id": 49,
    "type": "общий",
    "setup": "Почему в курятниках только две двери?",
    "punchline": "Потому что если бы их было четыре, это были бы куриные седаны"
  },
  {
    "id": 50,
    "type": "общий",
    "setup": "Как назвать фабрику, которая продает сносную продукцию?",
    "punchline": "Удовлетворительно"
  },
  {
    "id": 51,
    "type": "общий",
    "setup": "Когда папа проезжает мимо кладбища: вы знали, что это популярное кладбище?",
    "punchline": "Да, люди просто умирают от желания попасть туда"
  },
  {
    "id": 52,
    "type": "общий",
    "setup": "Почему человек-невидимка отклонил предложение о работе?",
    "punchline": "Он не мог представить себя делающим это"
  },
  {
    "id": 53,
    "type": "общий",
    "setup": "Как вы делаете святую воду?",
    "punchline": "Вы к чертям все это выварите"
  },
  {
    "id": 54,
    "type": "общий",
    "setup": "Прошлой ночью мне приснилось, что я был глушителем.",
    "punchline": "Я проснулась измученной!"
  },
  {
    "id": 55,
    "type": "общий",
    "setup": "Почему Питер Пэн всегда летает?",
    "punchline": "Потому что он никогда не приземляется"
  },
  {
    "id": 56,
    "type": "программирование",
    "setup": "Как проверить, является ли веб-страница HTML5?",
    "punchline": "Попробуйте в Internet Explorer"
  },
  {
    "id": 57,
    "type": "общий",
    "setup": "Как назвать корову без ног?",
    "punchline": "Говяжий фарш!"
  },
  {
    "id": 58,
    "type": "общий",
    "setup": "Сегодня утром я уронил грушу в машину.",
    "punchline": "Вы должны бросить еще один, тогда у вас будет пара."
  },
  {
    "id": 59,
    "type": "общий",
    "setup": "Леди: Как мне распространять любовь в этом жестоком мире?",
    "punchline": "Случайный чувак: [...💘]"
  },
  {
    "id": 60,
    "type": "программирование",
    "setup": "Пользовательский интерфейс похож на шутку.",
    "punchline": "Если тебе нужно это объяснять, то это не так уж и хорошо."
  },
  {
    "id": 61,
    "type": "тук-тук",
    "setup": "Тук-тук. \n Кто там? \n Хэтч. \n Хэтч кто?",
    "punchline": "Будь здоров!"
  },
  {
    "id": 62,
    "type": "общий",
    "setup": "Как вы называете грустный кофе?",
    "Punchline": "Деспрессо."
  },
  {
    "id": 63,
    "type": "общий",
    "setup": "Почему мясник работал в магазине сверхурочно?",
    "punchline": "Чтобы свести концы с концами."
  },
  {
    "id": 64,
    "type": "общий",
    "setup": "Вы слышали о голодных часах?",
    "punchline": "Прошло четыре секунды назад."
  },
  {
    "id": 65,
    "type": "общий",
    "setup": "Ну...",
    "punchline": "Это глубокая тема."
  },
  {
    "id": 66,
    "type": "общий",
    "setup": "Вы слышали историю о сыре, который спас мир?",
    "punchline": "Это была молочная легенда."
  },
  {
    "id": 67,
    "type": "общий",
    "setup": "Вы смотрели новый фильм по комиксам?",
    "punchline": "Это было очень наглядно!"
  },
  {
    "id": 68,
    "type": "общий",
    "setup": "В этом году я начал новый бизнес по производству яхт на чердаке...",
    "punchline": "Паруса пробивают крышу."
  },
  {
    "id": 69,
    "type": "общий",
    "setup": "Меня ударила по голове банка из-под газировки, но это было не так уж больно...",
    "punchline": "Это был безалкогольный напиток."
  },
  {
    "id": 70,
    "type": "общий",
    "setup": "Не могу сказать, нравится ли мне этот блендер...",
    "punchline": "Это продолжает давать мне смешанные результаты."
  },
  {
    "id": 71,
    "type": "общий",
    "setup": "Мне не удалось забронировать столик в библиотеке...",
    "punchline": "Они были полностью забронированы."
  },
  {
    "id": 72,
    "type": "программирование",
    "setup": "Я хотел рассказать вам анекдот про UDP...",
    "punchline": "...но вы можете не понять."
  },
  {
    "id": 73,
    "type": "программирование",
    "setup": "Кульминация часто появляется раньше, чем сетап.",
    "punchline": "Вы знаете, в чем проблема с UDP-шутками?"
  },
  {
    "id": 74,
    "type": "программирование",
    "setup": "Почему разработчики C# и Java продолжают ломать свои клавиатуры?",
    "punchline": "Потому что они используют строго typeизированный язык."
  },
  {
    "id": 75,
    "type": "общий",
    "setup": "Что подарить нуждающемуся лимону?",
    "Punchline": "Лимонад"
  },
  {
    "id": 76,
    "type": "общий",
    "setup": "Никогда не прислушивайтесь к советам электронов.",
    "punchline": "Они всегда отрицательные."
  },
  {
    "id": 78,
    "type": "общий",
    "setup": "Привет, пап, ты постригся?",
    "punchline": "Нет, я обосрался."
  },
  {
    "id": 79,
    "type": "общий",
    "setup": "Который час?",
    "punchline": "Я не знаю... это постоянно меняется."
  },
  {
    "id": 80,
    "type": "общий",
    "setup": "Ласка заходит в бар. Бармен говорит: \"Вау, я никогда раньше не обслуживал ласку. Что я могу получить для вас?\"",
    "punchline": "Поп, ласка идет."
  },
  {
    "id": 81,
    "type": "общий",
    "setup": "Плохо играешь в гольф?",
    "punchline": "Пошёл нахуй."
  },
  {
    "id": 82,
    "type": "общий",
    "setup": "Может ли кенгуру прыгнуть выше Эмпайр Стейт Билдинг?",
    "punchline": "Конечно. Эмпайр Стейт Билдинг не может прыгать."
  },
  {
    "id": 83,
    "type": "общий",
    "setup": "Может ли февраль маршировать?",
    "punchline": "Нет, но апрель может."
  },
  {
    "id": 84,
    "type": "общий",
    "setup": "Можно посмотреть телевизор?",
    "punchline": "Да, но не включайте."
  },
  {
    "id": 85,
    "type": "общий",
    "setup": "Папа, ты можешь надеть мои туфли?",
    "punchline": "Не думаю, что они мне подойдут."
  },
  {
    "id": 86,
    "type": "общий",
    "setup": "Вы слышали, что хлебозавод сгорел?",
    "punchline": "Говорят, бизнес поджарен."
  },
  {
    "id": 87,
    "type": "общий",
    "setup": "Вы слышали о хамелеоне, который не мог менять цвет?",
    "punchline": "У них была дисфункция рептилий."
  },
  {
    "id": 88,
    "type": "общий",
    "setup": "Вы слышали о взрыве сыроварни во Франции?",
    "punchline": "Не осталось ничего, кроме де Бри."
  },
  {
    "id": 89,
    "type": "общий",
    "setup": "Вы слышали про корову, перепрыгнувшую забор из колючей проволоки?",
    "punchline": "Это было разрушение вымени."
  },
  {
    "id": 90,
    "type": "общий",
    "setup": "Вы слышали о парне, который изобрел Lifesavers?",
    "punchline": "Говорят, он сделал монетный двор."
  },
  {
    "id": 91,
    "type": "общий",
    "setup": "Вы слышали о парне, у которого была отрезана вся левая сторона?",
    "punchline": "Сейчас с ним все в порядке."
  },
  {
    "id": 92,
    "type": "общий",
    "setup": "Вы слышали о похищении в школе?",
    "punchline": "Все в порядке, он проснулся."
  },
  {
    "id": 93,
    "type": "общий",
    "setup": "Вы слышали о мексиканском убийце поездов?",
    "punchline": "У него были локомотивы"
  },
  {
    "id": 94,
    "type": "общий",
    "setup": "Вы слышали о новом ресторане на Луне?",
    "punchline": "Еда отличная, но атмосферы нет."
  },
  {
    "id": 95,
    "type": "общий",
    "setup": "Вы слышали о бегуне, которого критиковали?",
    "punchline": "Он просто воспринял это как должное"
  },
  {
    "id": 96,
    "type": "общий",
    "setup": "Вы слышали об ученом, который был партнером по лаборатории с кастрюлей с кипящей водой?",
    "punchline": "У него был очень уважаемый коллега."
  },
  {
    "id": 97,
    "type": "общий",
    "setup": "Вы слышали о подводной промышленности?",
    "punchline": "Это действительно потребовало погружения..."
  },
  {
    "id": 98,
    "type": "общий",
    "setup": "Вы слышали, что Дэвид потерял свое удостоверение личности в Праге?",
    "punchline": "Теперь нам просто нужно звать его Дэв."
  },
  {
    "id": 99,
    "type": "общий",
    "setup": "Вы слышали, что у полиции есть ордер на карликового экстрасенса, грабящего людей?",
    "punchline": "Здесь написано \"Маленький средний в большом\""
  },
  {
    "id": 100,
    "type": "общий",
    "setup": "Слышали анекдот про странствующую монахиню?",
    "punchline": "Она была католичкой."
  },
  {
    "id": 101,
    "type": "общий",
    "setup": "Вы слышали новости?",
    "punchline": "FedEx и UPS объединяются. Отныне они будут называться Fed-Up."
  },
  {
    "id": 102,
    "type": "общий",
    "setup": "Вы слышали про парня со сломанным слуховым аппаратом?",
    "punchline": "Он тоже."
  },
  {
    "id": 103,
    "type": "общий",
    "setup": "Знаете ли вы, что крокодилы могут вырасти до 15 футов?",
    "punchline": "Но у большинства просто 4."
  },
  {
    "id": 104,
    "type": "общий",
    "setup": "Как призраки называют свою настоящую любовь?",
    "punchline": "Их друг-упырь"
  },
  {
    "id": 105,
    "type": "общий",
    "setup": "Знаете ли вы, что протоны имеют массу?",
    "punchline": "Я даже не знал, что они католики."
  },
  {
    "id": 106,
    "type": "общий",
    "setup": "Знаете ли вы, что для игры в гольф всегда нужно брать дополнительную пару штанов?",
    "punchline": "На всякий случай, если у вас будет дырка в одном."
  },
  {
    "id": 107,
    "type": "общий",
    "setup": "Нравится ли мне делать каламбуры в суде?",
    "Punchline": "Виновен"
  },
  {
    "id": 108,
    "type": "общий",
    "setup": "Вы знаете, где можно купить куриный бульон оптом?",
    "punchline": "Фондовый рынок."
  },
  {
    "id": 109,
    "type": "общий",
    "setup": "Хотите краткое объяснение того, что такое желудь?",
    "punchline": "Короче говоря, это дуб."
  },
  {
    "id": 110,
    "type": "общий",
    "setup": "Вы когда-нибудь задумывались, почему пчелы жужжат?",
    "punchline": "Это потому, что они не знают слов."
  },
  {
    "id": 112,
    "type": "общий",
    "setup": "Вы слышали о группе 1023MB?",
    "punchline": "У них еще нет концерта."
  },
  {
    "id": 113,
    "type": "общий",
    "setup": "Вы слышали, как ходят слухи о масле?",
    "punchline": "Неважно, я не должен это распространять."
  },
  {
    "id": 114,
    "type": "общий",
    "setup": "Чем вставные зубы похожи на звезды?",
    "punchline": "Они выходят ночью!"
  },
  {
    "id": 115,
    "type": "общий",
    "setup": "Как определить, что вампир простудился?",
    "punchline": "Они начинают гроб."
  },
  {
    "id": 116,
    "type": "общий",
    "setup": "Почему в человека, управляющего поездом, ударила молния?",
    "punchline": "Он был хорошим дирижером."
  },
  {
    "id": 117,
    "type": "общий",
    "setup": "Почему после игры стало жарко на стадионе?",
    "punchline": "Потому что все фанаты ушли."
  },
  {
    "id": 118,
    "type": "общий",
    "setup": "Откуда Дарт Вейдер узнал, что Люк получит на Рождество?",
    "punchline": "Он пощупал свои подарки."
  },
  {
    "id": 119,
    "type": "общий",
    "setup": "Как у хипстера сгорело небо?",
    "punchline": "Он съел пиццу до того, как она остыла."
  },
  {
    "id": 120,
    "type": "общий",
    "setup": "Как куры остаются в форме?",
    "punchline": "Они всегда делают яйца!"
  },
  {
    "id": 123,
    "type": "общий",
    "setup": "Как найти Уилла Смита в снегу?",
    "punchline": "Ищите свежие отпечатки."
  },
  {
    "id": 124,
    "type": "общий",
    "setup": "Как починить сломанную пиццу?",
    "punchline": "С томатной пастой."
  },
  {
    "id": 125,
    "type": "общий",
    "setup": "Как починить поврежденный фонарь из тыквы?",
    "punchline": "Вы используете тыквенный пластырь."
  },
  {
    "id": 126,
    "type": "общий",
    "setup": "Как уложить младенца-инопланетянина спать?",
    "punchline": "Ты ракета."
  },
  {
    "id": 127,
    "type": "общий",
    "setup": "Как посадить двух китов в машину?",
    "punchline": "Начните с Англии и езжайте на запад."
  },
  {
    "id": 128,
    "type": "общий",
    "setup": "Как узнать, что под кроватью слон?",
    "punchline": "Твоя голова бьется о потолок!"
  },
  {
    "id": 129,
    "type": "общий",
    "setup": "Как заставить носовой платок танцевать?",
    "punchline": "Добавьте немного буги-вуги."
  },
  {
    "id": 130,
    "type": "общий",
    "setup": "Как вы делаете святую воду?",
    "punchline": "Вы к чертям все это выварите."
  },
  {
    "id": 131,
    "type": "общий",
    "setup": "Как организовать космическую вечеринку?",
    "punchline": "Ты планета."
  },
  {
    "id": 132,
    "type": "общий",
    "setup": "Как украсть пальто?",
    "punchline": "Ты куртка."
  },
  {
    "id": 133,
    "type": "общий",
    "setup": "Как отличить крокодила от аллигатора?",
    "punchline": "Вы увидите один позже и один через некоторое время."
  },
  {
    "id": 134,
    "type": "общий",
    "setup": "Как пишет поэт-дислектик?",
    "punchline": "Обратное"
  },
  {
    "id": 135,
    "type": "общий",
    "setup": "Как французский скелет здоровается?",
    "punchline": "Кость-журн."
  },
  {
    "id": 136,
    "type": "общий",
    "setup": "Как пингвин строит свой дом?",
    "punchline": "Иглу вместе."
  },
  {
    "id": 137,
    "type": "общий",
    "setup": "Как ученому освежить дыхание?",
    "punchline": "С экспериментами!"
  },
  {
    "id": 138,
    "type": "общий",
    "setup": "Как луна подстригается?",
    "punchline": "Затмить это."
  },
  {
    "id": 139,
    "type": "общий",
    "setup": "Сколько яблок растет на дереве?",
    "punchline": "Все!"
  },
  {
    "id": 140,
    "type": "общий",
    "setup": "Сколько костей в руке человека?",
    "punchline": "Горстка из них."
  },
  {
    "id": 141,
    "type": "общий",
    "setup": "Сколько хипстеров нужно, чтобы поменять лампочку?",
    "punchline": "О, это действительно малоизвестный номер. Вероятно, вы никогда о нем не слышали."
  },
  {
    "id": 142,
    "type": "общий",
    "setup": "Сколько детей с СДВ нужно, чтобы поменять лампочку?",
    "punchline": "Поехали кататься на велосипедах!"
  },
  {
    "id": 143,
    "type": "общий",
    "setup": "Сколько оптометристов нужно, чтобы поменять лампочку?",
    "punchline": "1 или 2? 1... или 2?"
  },
  {
    "id": 144,
    "type": "общий",
    "setup": "Сколько секунд в году?",
    "punchline": "12. 2 января, 2 февраля, 2 марта, 2 апреля.... и т.д."
  },
  {
    "id": 145,
    "type": "общий",
    "setup": "Сколько жителей Южной Америки нужно, чтобы поменять лампочку?",
    "Punchline": "Бразильский"
  },
  {
    "id": 146,
    "type": "общий",
    "setup": "Сколько щекоток нужно, чтобы пощекотать осьминога?",
    "punchline": "Десять щекочет!"
  },
  {
    "id": 147,
    "type": "общий",
    "setup": "Сколько весит хипстер?",
    "punchline": "Инстаграм."
  },
  {
    "id": 148,
    "type": "общий",
    "setup": "Как чувствовал себя снежный шар после грозы?",
    "punchline": "Немного потрясен."
  },
  {
    "id": 149,
    "type": "общий",
    "setup": "Безопасен ли бассейн для дайвинга?",
    "punchline": "Это глубоко заканчивается."
  },
  {
    "id": 150,
    "type": "общий",
    "setup": "В вашей обуви есть дырка?",
    "punchline": "Нет... Тогда как ты в это попал?"
  },
  {
    "id": 151,
    "type": "общий",
    "setup": "Что спагетти сказали другим спагетти?",
    "punchline": "Pasta la vista, детка!"
  },
  {
    "id": 152,
    "type": "общий",
    "setup": "Как зовут 50 Cent в Зимбабве?",
    "Punchline": "200 долларов."
  },
  {
    "id": 153,
    "type": "общий",
    "setup": "Хотите услышать анекдот про дымоход?",
    "punchline": "Есть стопки их! Первый в доме"
  },
  {
    "id": 154,
    "type": "общий",
    "setup": "Хотите услышать анекдот про строительство?",
    "punchline": "Нет, я все еще работаю над этим."
  },
  {
    "id": 155,
    "type": "общий",
    "setup": "Хотите услышать мою шутку о пицце?",
    "punchline": "Неважно, это слишком глупо."
  },
  {
    "id": 156,
    "type": "общий",
    "setup": "Какое животное всегда присутствует на игре в крикет?",
    "punchline": "Летучая мышь."
  },
  {
    "id": 157,
    "type": "общий",
    "setup": "Какие самые сильные дни недели?",
    "punchline": "Суббота и воскресенье... остальные рабочие дни."
  },
  {
    "id": 158,
    "type": "общий",
    "setup": "Какое печенье нравится невысокому человеку?",
    "punchline": "Песочное печенье."
  },
  {
    "id": 159,
    "type": "общий",
    "setup": "Какой сыр никогда не будет твоим?",
    "Punchline": "Сыр начо."
  },
  {
    "id": 160,
    "type": "общий",
    "setup": "Какое существо умнее говорящего попугая?",
    "punchline": "Пчела по правописанию."
  },
  {
    "id": 161,
    "type": "общий",
    "setup": "Что сказал сельдерей, когда расстался со своей девушкой?",
    "punchline": "Она мне не подошла, так что я действительно не пряник."
  },
  {
    "id": 162,
    "type": "общий",
    "setup": "Как Майкл Джексон назвал свой джинсовый магазин?",
    "Punchline": "Билли Джинс!"
  },
  {
    "id": 163,
    "type": "общий",
    "setup": "Что сказал один псих, преследуя другого ореха?",
    "Punchline": "Я кешью!"
  },
  {
    "id": 164,
    "type": "общий",
    "setup": "Что одна тарелка сказала другой тарелке?",
    "punchline": "Ужин за мной!"
  },
  {
    "id": 165,
    "type": "общий",
    "setup": "Что один снеговик сказал другому снеговику?",
    "punchline": "Вы чувствуете запах моркови?"
  },
  {
    "id": 166,
    "type": "общий",
    "setup": "Что одна стена сказала другой стене?",
    "punchline": "Встретимся на углу!"
  },
  {
    "id": 167,
    "type": "общий",
    "setup": "Чем римляне резали пиццу до изобретения раскатки?",
    "punchline": "Лил Цезарь"
  },
  {
    "id": 168,
    "type": "общий",
    "setup": "Что 0 сказал 8?",
    "punchline": "Хороший пояс."
  },
  {
    "id": 169,
    "type": "общий",
    "setup": "Что бобер сказал дереву?",
    "punchline": "Было приятно погрызть тебя."
  },
  {
    "id": 170,
    "type": "общий",
    "setup": "Что большой цветок сказал маленькому цветку?",
    "punchline": "Привет, приятель!"
  },
  {
    "id": 180,
    "type": "общий",
    "setup": "Что сказал Бизон своему маленькому мальчику, когда подвозил его в школу?",
    "Punchline": "Бизон"
  },
  {
    "id": 181,
    "type": "общий",
    "setup": "Что цифровые часы сказали дедушкиным часам?",
    "punchline": "Смотрите, никаких рук!"
  },
  {
    "id": 182,
    "type": "общий",
    "setup": "Что собака сказала двум деревьям?",
    "punchline": "Кора кора."
  },
  {
    "id": 183,
    "type": "общий",
    "setup": "Что фермер из Дорито сказал другому фермеру из Дорито?",
    "punchline": "Крутое ранчо!"
  },
  {
    "id": 184,
    "type": "общий",
    "setup": "Что сказала рыба, когда вплыла в стену?",
    "Punchline": "Черт!"
  },
  {
    "id": 185,
    "type": "общий",
    "setup": "Что сделал виноград, когда на него наступили?",
    "punchline": "Он выпустил немного вина."
  },
  {
    "id": 186,
    "type": "общий",
    "setup": "Что судья сказал дантисту?",
    "punchline": "Вы клянетесь вырвать зуб, весь зуб и ничего, кроме зуба?"
  },
  {
    "id": 187,
    "type": "общий",
    "setup": "Что поздний помидор сказал раннему помидору?",
    "punchline": "Я наберу кетчуп"
  },
  {
    "id": 188,
    "type": "общий",
    "setup": "Что левый глаз сказал правому глазу?",
    "punchline": "Между нами что-то пахнет!"
  },
  {
    "id": 189,
    "type": "общий",
    "setup": "Как альпинист назвал своего сына?",
    "Punchline": "Утес."
  },
  {
    "id": 189,
    "type": "общий",
    "setup": "Что океан сказал пляжу?",
    "punchline": "Спасибо за осадок."
  },
  {
    "id": 190,
    "type": "общий",
    "setup": "Что океан сказал берегу?",
    "punchline": "Ничего, просто помахал."
  },
  {
    "id": 191,
    "type": "общий",
    "setup": "Почему вы не находите гиппопотамов, прячущихся на деревьях?",
    "punchline": "Они действительно хороши в этом."
  },
  {
    "id": 192,
    "type": "общий",
    "setup": "Что сказал пират на свое 80-летие?",
    "punchline": "Да, Мати!"
  },
  {
    "id": 193,
    "type": "общий",
    "setup": "Что красный свет сказал зеленому свету?",
    "punchline": "Не смотри на меня, я переодеваюсь!"
  },
  {
    "id": 194,
    "type": "общий",
    "setup": "Что шарф сказал шапке?",
    "punchline": "Идите вперед, я еще немного побуду."
  },
  {
    "id": 195,
    "type": "общий",
    "setup": "Что пожелал застенчивый камешек?",
    "punchline": "Что она была маленьким валуном."
  },
  {
    "id": 196,
    "type": "общий",
    "setup": "Что сказал светофор проезжающей машине?",
    "punchline": "Не смотри, я переодеваюсь!"
  },
  {
    "id": 197,
    "type": "общий",
    "setup": "Что дзен-буддист сказал продавцу хот-догов?",
    "punchline": "Сделай меня единым со всем."
  },
  {
    "id": 198,
    "type": "общий",
    "setup": "Что выдают птицы на Хэллоуин?",
    "punchline": "Твиты."
  },
  {
    "id": 199,
    "type": "общий",
    "setup": "Как я выгляжу?",
    "punchline": "МАШИНА ДЛЯ ШУТКИ!?"
  },
  {
    "id": 200,
    "type": "общий",
    "setup": "Как заключенные называют друг друга?",
    "punchline": "Мобильные телефоны."
  },
  {
    "id": 201,
    "type": "общий",
    "setup": "Что едят зомби-вегетарианцы?",
    "punchline": "Грррррайннннссссс."
  },
  {
    "id": 202,
    "type": "общий",
    "setup": "Как назвать медведя без зубов?",
    "punchline": "Мармеладный мишка!"
  },
  {
    "id": 203,
    "type": "общий",
    "setup": "Как назвать пчелу, которая живет в Америке?",
    "punchline": "USB."
  },
  {
    "id": 204,
    "type": "общий",
    "setup": "Как назвать бумеранг, который не вернется?",
    "punchline": "Палка."
  },
  {
    "id": 205,
    "type": "общий",
    "setup": "Как назвать осторожного волка?",
    "punchline": "Знающий волк."
  },
  {
    "id": 206,
    "type": "общий",
    "setup": "Как назвать корову на батуте?",
    "punchline": "Молочный коктейль!"
  },
  {
    "id": 207,
    "type": "общий",
    "setup": "Как назвать корову без ног?",
    "punchline": "Говяжий фарш."
  },
  {
    "id": 208,
    "type": "общий",
    "setup": "Как назвать корову с двумя ногами?",
    "punchline": "Постная говядина."
  },
  {
    "id": 209,
    "type": "общий",
    "setup": "Как назвать толпу шахматистов, хвастающихся своими победами в холле отеля?",
    "punchline": "Шахматные чокнутые хвастаются в открытом фойе."
  },
  {
    "id": 210,
    "type": "общий",
    "setup": "Как назвать папу, который провалился под лед?",
    "punchline": "Эскимо."
  },
  {
    "id": 211,
    "type": "общий",
    "setup": "Как называется словарь по наркотикам?",
    "punchline": "Высокое разрешение."
  },
  {
    "id": 212,
    "type": "общий",
    "setup": "как назвать собаку, которая умеет делать фокусы?",
    "Punchline": "лабракадабрадор"
  },
  {
    "id": 213,
    "type": "общий",
    "setup": "Как назвать дроида, который совершает долгий путь?",
    "punchline": "Объезд R2."
  },
  {
    "id": 214,
    "type": "общий",
    "setup": "Как назвать утку, которая получает все пятерки?",
    "punchline": "Мудрый шарлатан."
  },
  {
    "id": 215,
    "type": "общий",
    "setup": "Что вы называете фальшивой лапшой?",
    "punchline": "Импаста."
  },
  {
    "id": 216,
    "type": "общий",
    "setup": "Как назвать модную газонную статую с отличным чувством ритма?",
    "punchline": "Метро-гном"
  },
  {
    "id": 217,
    "type": "общий",
    "setup": "Как назвать толстого экстрасенса?",
    "punchline": "Кассир с четырьмя подбородками."
  },
  {
    "id": 218,
    "type": "общий",
    "setup": "Как назвать муху без крыльев?",
    "punchline": "Прогулка."
  },
  {
    "id": 219,
    "type": "общий",
    "setup": "Как назвать девушку между двумя постами?",
    "Punchline": "Аннет."
  },
  {
    "id": 220,
    "type": "общий",
    "setup": "Как назвать группу неорганизованных кошек?",
    "punchline": "Кот-тастрофа."
  },
  {
    "id": 221,
    "type": "общий",
    "setup": "Как назвать группу косаток, играющих на инструментах?",
    "Punchline": "Косатка-стра."
  },
  {
    "id": 222,
    "type": "общий",
    "setup": "Как назвать обезьяну на минном поле?",
    "Punchline": "Баооооум!"
  },
  {
    "id": 223,
    "type": "общий",
    "setup": "Как назвать нервного метателя копья?",
    "Punchline": "Шекспир."
  },
  {
    "id": 224,
    "type": "общий",
    "setup": "Как назвать свинью, которая занимается карате?",
    "punchline": "Свиная отбивная!"
  },
  {
    "id": 225,
    "type": "общий",
    "setup": "Как назвать свинью с тремя глазами?",
    "punchline": "Пииг"
  },
  {
    "id": 226,
    "type": "общий",
    "setup": "Как вы называете кучу кошек?",
    "Punchline": " Мяутейн."
  },
  {
    "id": 227,
    "type": "общий",
    "setup": "Как назвать овцу без ног?",
    "punchline": "Облако."
  },
  {
    "id": 228,
    "type": "общий",
    "setup": "Как назвать проблемного канадского старшеклассника?",
    "punchline": "Путин."
  },
  {
    "id": 229,
    "type": "общий",
    "setup": "Как назвать аллигатора в жилете?",
    "punchline": "Следователь!"
  },
  {
    "id": 230,
    "type": "общий",
    "setup": "Как назвать аргентинца с резиновым носком?",
    "punchline": "Роберто"
  },
  {
    "id": 231,
    "type": "общий",
    "setup": "Как назвать орла, который умеет играть на пианино?",
    "punchline": "Коготь!"
  },
  {
    "id": 232,
    "type": "общий",
    "setup": "Как назвать слона, который не имеет значения?",
    "punchline": "Бессловесный."
  },
  {
    "id": 233,
    "type": "общий",
    "setup": "Как назвать старого снеговика?",
    "Punchline": "Вода."
  },
  {
    "id": 234,
    "type": "общий",
    "setup": "Что вы сами называете сыром?",
    "punchline": "Проволоне"
  },
  {
    "id": 235,
    "type": "общий",
    "setup": "Как вы называете кукурузу, которая идет в армию?",
    "Punchline": "Ядро."
  },
  {
    "id": 236,
    "type": "общий",
    "setup": "Как назвать человека без носа?",
    "punchline": "Никто не знает."
  },
  {
    "id": 237,
    "type": "общий",
    "setup": "Как назвать двух барракуд?",
    "punchline": "Пайракуда!"
  },
  {
    "id": 238,
    "type": "общий",
    "setup": "Что вы делаете на отдаленном острове?",
    "punchline": "Попробуйте найти телевизионный остров, которому он принадлежит."
  },
  {
    "id": 239,
    "type": "общий",
    "setup": "Что вы делаете, когда видите космонавта?",
    "punchline": "Припаркуй машину, чувак."
  },
  {
    "id": 240,
    "type": "общий",
    "setup": "Что у вас висит на яблонях?",
    "punchline": "Больные руки."
  },
  {
    "id": 241,
    "type": "общий",
    "setup": "Что получится, если скрестить пчелу и овцу?",
    "Punchline": "Бах-обман."
  },
  {
    "id": 242,
    "type": "общий",
    "setup": "Что получится, если скрестить курицу со скунсом?",
    "punchline": "Птичий запах!"
  },
  {
    "id": 243,
    "type": "общий",
    "setup": "Что получится, если скрестить кролика с водяным шлангом?",
    "punchline": "Заячий спрей."
  },
  {
    "id": 244,
    "type": "общий",
    "setup": "Что получится, если скрестить снеговика с вампиром?",
    "punchline": "Обморожение."
  },
  {
    "id": 245,
    "type": "общий",
    "setup": "Что дать больному лимону?",
    "Punchline": "Лимонад"
  },
  {
    "id": 246,
    "type": "общий",
    "setup": "Что делают часы, когда голодны?",
    "punchline": "Четыре секунды назад!"
  },
  {
    "id": 247,
    "type": "общий",
    "setup": "Что использует самка змеи для поддержки?",
    "punchline": "Ко-Бюстгальтер!"
  },
  {
    "id": 248,
    "type": "общий",
    "setup": "Сколько пират платит за свою кукурузу?",
    "punchline": "Буканьер!"
  },
  {
    "id": 249,
    "type": "общий",
    "setup": "Что делает злой перец?",
    "punchline": "Это лицо халапеньо."
  },
  {
    "id": 250,
    "type": "общий",
    "setup": "Что происходит с машиной лягушки, когда она ломается?",
    "punchline": "Это становится жабой."
  },
  {
    "id": 251,
    "type": "общий",
    "setup": "Что произойдет, если вы разозлите нейрохирурга?",
    "punchline": "Они поделятся с вами своим мнением."
  },
  {
    "id": 252,
    "type": "общий",
    "setup": "Что имеет уши, но не слышит?",
    "punchline": "Кукурузное поле."
  },
  {
    "id": 253,
    "type": "общий",
    "setup": "Какая любимая песня сороконожек из группы \"Битлз\"?",
    "punchline": "Я хочу держать тебя за руку, за руку, за руку, за руку..."
  },
  {
    "id": 254,
    "type": "общий",
    "setup": "В какую любимую игру торнадо играть?",
    "punchline": "Твистер!"
  },
  {
    "id": 255,
    "type": "общий",
    "setup": "Какой любимый фрукт вампира?",
    "punchline": "Красный апельсин."
  },
  {
    "id": 256,
    "type": "общий",
    "setup": "Какой любимый предмет ведьмы в школе?",
    "punchline": "Правописание!"
  },
  {
    "id": 257,
    "type": "общий",
    "setup": "Что такое красное и пахнет синей краской?",
    "punchline": "Красная краска!"
  },
  {
    "id": 258,
    "type": "общий",
    "setup": "В чем разница между невежеством и апатией?",
    "punchline": "Я не знаю, и мне все равно."
  },
  {
    "id": 259,
    "type": "общий",
    "setup": "Что самое сложное в прыжках с парашютом?",
    "Punchline": "Земля."
  },
  {
    "id": 260,
    "type": "общий",
    "setup": "Какова основная причина сухости кожи?",
    "punchline": "Полотенца"
  },
  {
    "id": 261,
    "type": "общий",
    "setup": "На каком языке говорят меньше всего в мире?",
    "punchline": "Язык жестов"
  },
  {
    "id": 262,
    "type": "общий",
    "setup": "Какое самое высокое здание в мире?",
    "punchline": "В библиотеке больше всего историй!"
  },
  {
    "id": 263,
    "type": "общий",
    "setup": "О чем этот фильм?",
    "punchline": "Это примерно 2 часа."
  },
  {
    "id": 264,
    "type": "общий",
    "setup": "Какую награду получил стоматолог?",
    "punchline": "Небольшая табличка."
  },
  {
    "id": 265,
    "type": "общий",
    "setup": "Какой бублик может летать?",
    "punchline": "Обычный рогалик."
  },
  {
    "id": 266,
    "type": "общий",
    "setup": "Какой динозавр любит спать?",
    "punchline": "Стега-храпит-нас."
  },
  {
    "id": 267,
    "type": "общий",
    "setup": "Что за собака живет в ускорителе частиц?",
    "Punchline": "Фермилабрадорский ретривер."
  },
  {
    "id": 268,
    "type": "общий",
    "setup": "В какую магию верят коровы?",
    "punchline": "MOODOO."
  },
  {
    "id": 269,
    "type": "общий",
    "setup": "Какую музыку слушают планеты?",
    "punchline": "Неп-мелодии."
  },
  {
    "id": 270,
    "type": "общий",
    "setup": "Какие брюки носят призраки?",
    "Punchline": "Джинсы Бу."
  },
  {
    "id": 271,
    "type": "общий",
    "setup": "Какое дерево помещается в вашей руке?",
    "punchline": "Пальма!"
  },
  {
    "id": 272,
    "type": "общий",
    "setup": "Что лежит на дне океана и дергается?",
    "punchline": "Нервный срыв."
  },
  {
    "id": 273,
    "type": "общий",
    "setup": "Какой музыкальный инструмент находится в ванной?",
    "punchline": "Зубная паста из тубы."
  },
  {
    "id": 274,
    "type": "общий",
    "setup": "Во сколько мужчина пошел к стоматологу?",
    "punchline": "Зуб болит."
  },
  {
    "id": 275,
    "type": "общий",
    "setup": "Какую музыку ненавидят воздушные шары?",
    "punchline": "Поп-музыка!"
  },
  {
    "id": 276,
    "type": "общий",
    "setup": "Что было более важным изобретением, чем первый телефон?",
    "punchline": "Второй."
  },
  {
    "id": 277,
    "type": "общий",
    "setup": "Какой любимый вид спорта у тыквы?",
    "Punchline": "Сквош."
  },
  {
    "id": 278,
    "type": "общий",
    "setup": "Что такое черно-белое и сплошное чтение?",
    "Punchline": "Газета."
  },
  {
    "id": 279,
    "type": "общий",
    "setup": "Что такое синее и не очень тяжелое?",
    "punchline": "Голубой."
  },
  {
    "id": 280,
    "type": "общий",
    "setup": "Что коричневое и липкое?",
    "punchline": "Палка."
  },
  {
    "id": 281,
    "type": "общий",
    "setup": "Что такое оранжевый и звучит как попугай?",
    "Punchline": "Морковь."
  },
  {
    "id": 282,
    "type": "общий",
    "setup": "Что краснеет и вредно для зубов?",
    "Punchline": "Кирпич."
  },
  {
    "id": 283,
    "type": "общий",
    "setup": "Что самое лучшее в шутках про лифт?",
    "punchline": "Они работают на очень многих уровнях."
  },
  {
    "id": 284,
    "type": "общий",
    "setup": "В чем разница между гитарой и рыбой?",
    "punchline": "Вы можете настроить гитару, но не сможете \"тунца\"ловить рыбу!"
  },
  {
    "id": 285,
    "type": "общий",
    "setup": "В чем разница между бегемотом и zippo?",
    "punchline": "Один действительно тяжелый, другой немного легче."
  },
  {
    "id": 286,
    "type": "общий",
    "setup": "В чем разница между тюленем и морским львом?",
    "punchline": "Ион!"
  },
  {
    "id": 287,
    "type": "общий",
    "setup": "Что самое худшее в том, чтобы быть косоглазым учителем?",
    "punchline": "Они не могут контролировать своих учеников."
  },
  {
    "id": 288,
    "type": "общий",
    "setup": "Что самое худшее на уроке древней истории?",
    "punchline": "Учителя стремятся к Вавилону."
  },
  {
    "id": 289,
    "type": "общий",
    "setup": "Что коричневого цвета и звучит как колокольчик?",
    "Punchline": "Навоз!"
  },
  {
    "id": 290,
    "type": "общий",
    "setup": "Что такое сокращение от ET?",
    "punchline": "У него только маленькие ножки."
  },
  {
    "id": 291,
    "type": "общий",
    "setup": "Какой у Форест Гампа пароль на Facebook?",
    "punchline": "1forest1"
  },
  {
    "id": 292,
    "type": "общий",
    "setup": "В чем преимущество жизни в Швейцарии?",
    "punchline": "Ну, флаг - это большой плюс."
  },
  {
    "id": 293,
    "type": "общий",
    "setup": "В чем разница между африканским слоном и индийским слоном?",
    "punchline": "Около 5000 миль."
  },
  {
    "id": 294,
    "type": "общий",
    "setup": "Когда врачи злятся?",
    "punchline": "Когда у них кончатся пациенты."
  },
  {
    "id": 295,
    "type": "общий",
    "setup": "Когда шутка становится папиной шуткой?",
    "punchline": "Когда это станет очевидным."
  },
  {
    "id": 296,
    "type": "общий",
    "setup": "Когда дверь не дверь?",
    "punchline": "Когда он приоткрыт."
  },
  {
    "id": 297,
    "type": "общий",
    "setup": "Где вы научились делать мороженое?",
    "punchline": "Воскресная школа."
  },
  {
    "id": 298,
    "type": "общий",
    "setup": "Куда пчелы ходят в туалет?",
    "Punchline": "Станция ВР."
  },
  {
    "id": 299,
    "type": "общий",
    "setup": "Где танцуют гамбургеры?",
    "punchline": "Фитболка."
  },
  {
    "id": 300,
    "type": "общий",
    "setup": "Куда идут кролики после свадьбы?",
    "Punchline": "На луне-кролике."
  },
  {
    "id": 301,
    "type": "общий",
    "setup": "Куда ходят овцы стричься?",
    "punchline": "Магазин баа-баа."
  },
  {
    "id": 302,
    "type": "общий",
    "setup": "Где научиться делать банановый сплит?",
    "punchline": "В школе мороженого."
  },
  {
    "id": 303,
    "type": "общий",
    "setup": "Где молодые коровы обедают?",
    "punchline": "В икры-атерии."
  },
  {
    "id": 304,
    "type": "общий",
    "setup": "Где Бэтмен ходит в туалет?",
    "punchline": "В туалете."
  },
  {
    "id": 305,
    "type": "общий",
    "setup": "Куда Фонзи любит ходить на обед?",
    "Punchline": "Чик-Фил-Эйииииииииии."
  },
  {
    "id": 306,
    "type": "общий",
    "setup": "Где Наполеон держит свои армии?",
    "punchline": "В рукавах."
  },
  {
    "id": 307,
    "type": "общий",
    "setup": "Где была подписана Декларация независимости?",
    "punchline": "На дне!"
  },
  {
    "id": 308,
    "type": "общий",
    "setup": "Где корзина?",
    "punchline": "Я нигде не был!"
  },
  {
    "id": 309,
    "type": "общий",
    "setup": "На какой стороне курицы больше перьев?",
    "punchline": "Снаружи."
  },
  {
    "id": 310,
    "type": "общий",
    "setup": "На ком женился волшебник?",
    "punchline": "Его друг-гуль"
  },
  {
    "id": 311,
    "type": "общий",
    "setup": "Кто самый крутой Доктор в больнице?",
    "punchline": "Доктор бедра!"
  },
  {
    "id": 312,
    "type": "общий",
    "setup": "Почему рыбу легко взвешивать?",
    "punchline": "Потому что у них свои весы."
  },
  {
    "id": 313,
    "type": "общий",
    "setup": "Почему рыбы такие умные?",
    "punchline": "Потому что они живут в школах!"
  },
  {
    "id": 314,
    "type": "общий",
    "setup": "Почему призраки плохие лжецы?",
    "punchline": "Потому что вы можете видеть сквозь них!"
  },
  {
    "id": 315,
    "type": "общий",
    "setup": "Почему на кладбищах так шумно?",
    "punchline": "Из-за всего этого гроба."
  },
  {
    "id": 316,
    "type": "общий",
    "setup": "Почему мамочки боятся отпуска?",
    "punchline": "Они боятся расслабиться."
  },
  {
    "id": 317,
    "type": "общий",
    "setup": "Почему апельсины - самые умные фрукты?",
    "punchline": "Потому что они созданы для концентрации."
  },
  {
    "id": 318,
    "type": "общий",
    "setup": "Почему пиратов называют пиратами?",
    "punchline": "Потому что они стреляют!"
  },
  {
    "id": 319,
    "type": "общий",
    "setup": "Почему скелеты такие спокойные?",
    "punchline": "Потому что им ничего не задевает."
  },
  {
    "id": 320,
    "type": "общий",
    "setup": "Почему велосипед не может стоять сам по себе?",
    "punchline": "Это надоело."
  },
  {
    "id": 321,
    "type": "общий",
    "setup": "Почему нельзя использовать \"Beef stew\" в качестве пароля?",
    "punchline": "Потому что это не бефстроганов."
  },
  {
    "id": 322,
    "type": "общий",
    "setup": "Почему ваш нос не может быть 12 дюймов в длину?",
    "punchline": "Потому что тогда это была бы нога!"
  },
  {
    "id": 323,
    "type": "общий",
    "setup": "Почему вы не слышите, как птеродактиль идет в туалет?",
    "punchline": "П молчит."
  },
  {
    "id": 324,
    "type": "общий",
    "setup": "Почему ребенок не смог посмотреть фильм про пиратов?",
    "punchline": "Потому что у него рейтинг а-р-р!"
  },
  {
    "id": 325,
    "type": "общий",
    "setup": "Почему спасатель не смог спасти хиппи?",
    "punchline": "Он был слишком далеко, чувак."
  },
  {
    "id": 326,
    "type": "общий",
    "setup": "Почему Дракула лежал не в том гробу?",
    "punchline": "Он совершил серьезную ошибку."
  },
  {
    "id": 327,
    "type": "общий",
    "setup": "Почему Швеция начала рисовать штрих-коды на бортах своих линкоров?",
    "punchline": "Значит, они могли по-скандинавски."
  },
  {
    "id": 328,
    "type": "общий",
    "setup": "Почему буква А пошла в ванную, а вышла как буква Е?",
    "punchline": "Потому что у него было движение гласных."
  },
  {
    "id": 329,
    "type": "общий",
    "setup": "Почему парикмахер выиграл гонку?",
    "punchline": "Он срезал путь."
  },
  {
    "id": 330,
    "type": "общий",
    "setup": "Почему ремень попал в тюрьму?",
    "punchline": "Он поднял штаны!"
  },
  {
    "id": 331,
    "type": "общий",
    "setup": "Почему грабитель повесил свою фотографию на стену?",
    "punchline": "Чтобы доказать, что его подставили!"
  },
  {
    "id": 332,
    "type": "общий",
    "setup": "Почему курица получила штраф?",
    "punchline": "Для охоты."
  },
  {
    "id": 333,
    "type": "общий",
    "setup": "Почему Клайдсдейл дал пони стакан воды?",
    "punchline": "Потому что он был маленькой лошадкой!"
  },
  {
    "id": 334,
    "type": "общий",
    "setup": "Почему кофе написал заявление в полицию?",
    "punchline": "Он ограблен."
  },
  {
    "id": 335,
    "type": "общий",
    "setup": "Почему печенька плакала?",
    "punchline": "Потому что его мать так долго была облаткой"
  },
  {
    "id": 336,
    "type": "общий",
    "setup": "Почему печенька плакала?",
    "punchline": "Это было рассыпчато."
  },
  {
    "id": 337,
    "type": "общий",
    "setup": "Почему у ковбоя была собака-вайнер?",
    "punchline": "Кто-то сказал ему сделать длинную маленькую собачку."
  },
  {
    "id": 338,
    "type": "общий",
    "setup": "Почему у пожарного были красные, белые и синие подтяжки?",
    "punchline": "Чтобы подержать штаны."
  },
  {
    "id": 339,
    "type": "общий",
    "setup": "Почему девушка размазала по дороге арахисовое масло?",
    "punchline": "Ехать в пробке."
  },
  {
    "id": 340,
    "type": "общий",
    "setup": "Почему полуслепой упал в колодец?",
    "punchline": "Потому что он плохо видел!"
  },
  {
    "id": 341,
    "type": "общий",
    "setup": "Почему дома пошли к врачу?",
    "punchline": "У него были оконные стекла."
  },
  {
    "id": 342,
    "type": "общий",
    "setup": "Почему ребенок перешел детскую площадку?",
    "punchline": "Чтобы перейти к другому слайду."
  },
  {
    "id": 343,
    "type": "общий",
    "setup": "Почему мужчина положил деньги в морозилку?",
    "punchline": "Он хотел холодную наличку!"
  },
  {
    "id": 344,
    "type": "общий",
    "setup": "Почему мужчина бегал вокруг своей кровати?",
    "punchline": "Потому что он пытался отоспаться!"
  },
  {
    "id": 345,
    "type": "общий",
    "setup": "Почему дыни спланировали большую свадьбу?",
    "punchline": "Потому что они дыни!"
  },
  {
    "id": 346,
    "type": "общий",
    "setup": "Почему осьминог победил акулу в драке?",
    "punchline": "Потому что он был хорошо вооружен."
  },
  {
    "id": 347,
    "type": "общий",
    "setup": "Почему оперный певец ушел в плавание?",
    "punchline": "Они хотели достичь высоких C."
  },
  {
    "id": 348,
    "type": "общий",
    "setup": "Почему чучело получило награду?",
    "punchline": "Потому что он был выдающимся в своей области."
  },
  {
    "id": 349,
    "type": "общий",
    "setup": "Почему помидор покраснел?",
    "punchline": "Потому что он увидел заправку для салата."
  },
  {
    "id": 350,
    "type": "общий",
    "setup": "Почему дерево пошло к стоматологу?",
    "punchline": "Нужен корневой канал."
  },
  {
    "id": 351,
    "type": "общий",
    "setup": "Почему работника уволили с завода по производству апельсинового сока?",
    "punchline": "Недостаток концентрации."
  },
  {
    "id": 352,
    "type": "общий",
    "setup": "Почему номер 4 не попал в ночной клуб?",
    "punchline": "Потому что он 2-й квадрат."
  },
  {
    "id": 353,
    "type": "общий",
    "setup": "Почему апельсин не выиграл гонку?",
    "punchline": "Кончился сок."
  },
  {
    "id": 354,
    "type": "общий",
    "setup": "Почему скелет не перешел дорогу?",
    "punchline": "Потому что у него не хватило смелости."
  },
  {
    "id": 355,
    "type": "общий",
    "setup": "Почему бананы должны наносить солнцезащитный крем перед тем, как пойти на пляж?",
    "punchline": "Потому что они могут отклеиться!"
  },
  {
    "id": 356,
    "type": "общий",
    "setup": "Почему у медведей мохнатая шуба?",
    "punchline": "Меховая защита."
  },
  {
    "id": 357,
    "type": "общий",
    "setup": "Почему у пчел липкие волосы?",
    "punchline": "Потому что они используют медовые соты!"
  },
  {
    "id": 358,
    "type": "общий",
    "setup": "Почему пчелы жужжат?",
    "punchline": "Потому что они не знают слов."
  },
  {
    "id": 359,
    "type": "общий",
    "setup": "Почему птицы улетают на юг на зимовку?",
    "punchline": "Потому что идти слишком далеко."
  },
  {
    "id": 360,
    "type": "общий",
    "setup": "Почему хоры держат под рукой ведра?",
    "punchline": "Чтобы они могли нести свою мелодию"
  },
  {
    "id": 361,
    "type": "общий",
    "setup": "Почему крабы никогда не жертвуют на благотворительность?",
    "punchline": "Потому что это моллюски."
  },
  {
    "id": 362,
    "type": "общий",
    "setup": "Почему из уток получаются отличные детективы?",
    "punchline": "Они всегда шарлатанствуют."
  },
  {
    "id": 363,
    "type": "общий",
    "setup": "Почему математики ненавидят США?",
    "punchline": "Потому что он неделим."
  },
  {
    "id": 364,
    "type": "общий",
    "setup": "Почему пираты не знают алфавит?",
    "punchline": "Они всегда застревают на \"C\"."
  },
  {
    "id": 365,
    "type": "общий",
    "setup": "Почему тыквы сидят у людей на подъездах?",
    "punchline": "У них нет рук, чтобы стучать в дверь."
  },
  {
    "id": 366,
    "type": "общий",
    "setup": "Почему аквалангисты падают в воду задом наперёд?",
    "punchline": "Потому что, если они упадут вперед, они все еще будут в лодке."
  },
  {
    "id": 367,
    "type": "общий",
    "setup": "Почему в солнечные дни деревья кажутся подозрительными?",
    "punchline": "Не знаю, они просто немного подозрительны."
  },
  {
    "id": 368,
    "type": "общий",
    "setup": "Почему девушки из долины тусуются нечетными группами?",
    "punchline": "Потому что они даже не могут."
  },
  {
    "id": 369,
    "type": "общий",
    "setup": "Почему волшебники чистят зубы три раза в день?",
    "punchline": "Чтобы предотвратить дыхание летучих мышей!"
  },
  {
    "id": 370,
    "type": "общий",
    "setup": "Почему вы никогда не видите слонов, прячущихся на деревьях?",
    "punchline": "Потому что они так хороши в этом."
  },
  {
    "id": 371,
    "type": "общий",
    "setup": "Почему в курятнике только две двери?",
    "punchline": "Потому что, если бы у него было четыре двери, это был бы куриный седан."
  },
  {
    "id": 372,
    "type": "общий",
    "setup": "Почему лунный камень вкуснее земного?",
    "punchline": "Потому что это маленький метеор."
  },
  {
    "id": 373,
    "type": "общий",
    "setup": "Почему перемещение с 1-й на 2-ю базу занимает больше времени, чем со 2-й на 3-ю базу?",
    "punchline": "Потому что между ними есть шорт-стоп!"
  },
  {
    "id": 374,
    "type": "общий",
    "setup": "Почему у Норвегии на линкорах штрих-коды?",
    "punchline": "Значит, когда они вернутся в порт, они смогут поскандинавски."
  },
  {
    "id": 375,
    "type": "общий",
    "setup": "Почему Супермена приглашают на обеды?",
    "punchline": "Потому что он Супергерой."
  },
  {
    "id": 376,
    "type": "общий",
    "setup": "Почему Уолдо носит только полоски?",
    "punchline": "Потому что он не хочет, чтобы его заметили."
  },
  {
    "id": 377,
    "type": "программирование",
    "setup": "Тук-тук.",
    "punchline": "Состояние гонки. Кто там?"
  },
  {
    "id": 378,
    "type": "программирование",
    "setup": "Что самое лучшее в шутках про TCP?",
    "punchline": "Я буду говорить им, пока вы их не получите."
  },
  {
    "id": 379,
    "type": "программирование",
    "setup": "Программист перед сном ставит два стакана на тумбочку.",
    "punchline": "Полный, на случай, если он захочет пить, и пустой, если не захочет."
  },
  {
    "id": 380,
    "type": "программирование",
    "setup": "В этом мире есть 10 typeов людей.",
    "punchline": "Те, кто понимает двоичную систему, те, кто не понимает, и те, кто не ожидал шутки с основанием 3."
  },
  {
    "id": 381,
    "type": "общий",
    "setup": "Два парня заходят в бар...",
    "punchline": "Первый парень говорит \"Ой!\", а второй говорит \"Да, я тоже этого не видел\""
  },
  {
    "id": 382,
    "type": "программирование",
    "setup": "Что маршрутизатор сказал врачу?",
    "punchline": "Больно, когда IP."
  },
  {
    "id": 383,
    "type": "программирование",
    "setup": "Из дома выходит пакет IPv6.",
    "punchline": "Он никуда не уходит."
  },
  {
    "id": 384,
    "type": "программирование",
    "setup": "Пакет DHCP заходит в бар и просит пива.",
    "punchline": "Бармен говорит: \"вот, но он мне понадобится через час!\""
  },
  {
    "id": 385,
    "type": "программирование",
    "setup": "3 оператора SQL входят в панель NoSQL. Вскоре они выходят",
    "punchline": "Они не смогли найти стол."
  },
  {
    "id": 386,
    "type": "общий",
    "setup": "Я видел хорошую стереосистему на Craigslist за 1 доллар. Продавец говорит, что громкость застряла на \"высокой\"",
    "punchline": "Я не мог отказаться."
  },
  {
    "id": 387,
    "type": "общий",
    "setup": "Мой старший брат всегда рвал последние страницы моих комиксов и никогда не говорил мне почему.",
    "punchline": "Мне пришлось сделать собственные выводы."
  },
  {
    "id": 387,
    "type": "общий",
    "setup": "Ржака",
    "punchline": "Ржомба"
  },
  {
    "id": 387,
    "type": "общий",
    "setup": "Пиздец",
    "punchline": "Обосраля"
  },
  {
    "id": 387,
    "type": "общий",
    "setup": "АХАХАахахАХАХАХХХа",
    "punchline": "Вы видели этого?"
  },
  {
    "id": 387,
    "type": "общий",
    "setup": "Что за хуйня?",
    "punchline": "?"
  },
  {
    "id": 387,
    "type": "общий",
    "setup": "Вы видели этого человека",
    "punchline": ""
  },
  {
    "id": 387,
    "type": "общий",
    "setup": "Гейб ньюел",
    "punchline": ""
  },
  {
    "id": 387,
    "type": "общий",
    "setup": "я очень голодный",
    "punchline": "я очень голодный"
  },
  {
    "id": 387,
    "type": "общий",
    "setup": "ржу",
    "punchline": ""
  },
  {
    "id": 387,
    "type": "общий",
    "setup": "Понятно",
    "punchline": " "
  },
  {
    "id": 387,
    "type": "общий",
    "setup": "И шо поделать",
    "punchline": "а шо ты хотел"
  },
  {
    "id": 387,
    "type": "общий",
    "setup": "Ты смог убить ебаный защитник виндоус?",
    "punchline": " "
  },
  {
    "id": 387,
    "type": "общий",
    "setup": "Finally",
    "punchline": " "
  },
  {
    "id": 387,
    "type": "общий",
    "setup": "Finally",
    "punchline": "Finally"
  },
  {
    "id": 387,
    "type": "общий",
    "setup": "Просто пиздец",
    "punchline": "Она из шанхая учится в бгу"
  },
  {
    "id": 387,
    "type": "общий",
    "setup": "Попробовал я вашу эту попла коклу...",
    "punchline": "..."
  },
  {
    "id": 387,
    "type": "общий",
    "setup": "Теперь я выгляжу так",
    "punchline": "Теперь я выгляжу так"
  },
  {
    "id": 387,
    "type": "общий",
    "setup": "я сейчас смотрел это и мама подумала что я смотрю на котов",
    "punchline": "а на самом деле я обосрался"
  },
  {
    "id": 387,
    "type": "общий",
    "setup": "Боролся с ватой в интернете, Мне сказали что я диванный",
    "punchline": "А я кроватный"
  },
  {
    "id": 387,
    "type": "общий",
    "setup": "Чел харош",
    "punchline": " "
  },
  {
    "id": 387,
    "type": "общий",
    "setup": "Переедешь в польшу вся еда будет такой",
    "punchline": "Еще и бесплатно"
  },
  {
    "id": 387,
    "type": "общий",
    "setup": "Адидас бэсикс",
    "punchline": " "
  },
  {
    "id": 387,
    "type": "общий",
    "setup": "Цены на рейсы «Аэрофлота» и «Red Wings» в Азербайджан, Армению и Анталию.",
    "punchline": " "
  },
  {
    "id": 387,
    "type": "общий",
    "setup": "Ты сомневаешься в достоверности информации?",
    "punchline": " "
  },
  {
    "id": 387,
    "type": "общий",
    "setup": "А че, сексуальный мужчина..",
    "punchline": " "
  },
  {
    "id": 387,
    "type": "общий",
    "setup": "Фанаты \"Зелёного слоника\" оценят.",
    "punchline": " "
  },
  {
    "id": 387,
    "type": "общий",
    "setup": "ахуенна воу воуоу",
    "punchline": "уоу уооу"
  },
  {
    "id": 387,
    "type": "общий",
    "setup": "что делает функция, которая называется двойные субтитры",
    "punchline": "помогите"
  },
  {
    "id": 387,
    "type": "общий",
    "setup": "вот так я выгляжу",
    "punchline": " "
  },
  {
    "id": 387,
    "type": "общий",
    "setup": "я тоже",
    "punchline": " "
  },
  {
    "id": 387,
    "type": "общий",
    "setup": "согл",
    "punchline": " "
  },
  {
    "id": 387,
    "type": "общий",
    "setup": "у девочки приятный голос",
    "punchline": "ахахаха"
  },
  {
    "id": 387,
    "type": "общий",
    "setup": "интернет спиздили",
    "punchline": " "
  },
  {
    "id": 387,
    "type": "общий",
    "setup": "похуй",
    "punchline": "и че"
  },
  {
    "id": 387,
    "type": "общий",
    "setup": "вы такое пропускаете",
    "punchline": "вы бы знали"
  }
]
  